README.md
setup.py
argcomb/__init__.py
argcomb/argcomb.py
argcomb.egg-info/PKG-INFO
argcomb.egg-info/SOURCES.txt
argcomb.egg-info/dependency_links.txt
argcomb.egg-info/top_level.txt