Metadata-Version: 2.1
Name: argcomb
Version: 1.0.1
Summary: A simple library for building command-line arguments
Home-page: https://github.com/percyliang/argcomb
Author: Percy Liang
Author-email: percyliang@gmail.com
License: MIT
Keywords: command-line
Platform: UNKNOWN
Classifier: Programming Language :: Python :: 3
Classifier: License :: OSI Approved :: MIT License
Classifier: Operating System :: OS Independent
Requires-Python: >=3.6
